polygeohasher/__init__.py
polygeohasher/converters.py
polygeohasher/core.py
polygeohasher/polygeohasher.py
polygeohasher/polygon_geohash_convertor.py
polygeohasher/utils.py
polygeohasher-1.1.0.dist-info/LICENCE.txt
polygeohasher-1.1.0.dist-info/METADATA
polygeohasher-1.1.0.dist-info/WHEEL
polygeohasher-1.1.0.dist-info/RECORD
