Metadata-Version: 2.3
Name: polygeohasher
Version: 1.1.0
Summary: A complete package to work with polygons and geohashes. Optimisation of Geohash levels to cover and area with % error controlled by user. Also allows to convert geohases to polygons.
Author: krishna khadka
Author-email: krishnakhadka2802@gmail.com
Requires-Python: >=3.9,<4.0
Classifier: Programming Language :: Python :: 3
Classifier: Programming Language :: Python :: 3.9
Classifier: Programming Language :: Python :: 3.10
Classifier: Programming Language :: Python :: 3.11
Classifier: Programming Language :: Python :: 3.12
Classifier: Programming Language :: Python :: 3.13
Requires-Dist: geohash (>=1.0,<2.0)
Requires-Dist: geopandas (>=0.14.2,<0.15.0)
Requires-Dist: shapely (>=2.0.2,<3.0.0)
